nasp/__init__.py
nasp/configuration_parser.py
nasp/convert_external_genome.py
nasp/dispatcher.py
nasp/find_duplicates.py
nasp/format_fasta.py
nasp/illumina_adapters_all.fasta
nasp/matrix_DTO.py
nasp/nasp.py
nasp/nasp_objects.py
nasp/nasptool_linux_32
nasp/nasptool_linux_64
nasp/vcf_to_matrix.py
nasp-1.1.2.data/scripts/filter_matrix_by_coord.py
nasp-1.1.2.data/scripts/filter_matrix_by_distance.py
nasp-1.1.2.data/scripts/filter_matrix_by_genome.py
nasp-1.1.2.data/scripts/matrix_to_fasta.py
nasp-1.1.2.data/scripts/merge_matrices.py
nasp-1.1.2.data/scripts/report_single_snps_single_isolate.py
nasp-1.1.2.dist-info/METADATA
nasp-1.1.2.dist-info/RECORD
nasp-1.1.2.dist-info/WHEEL
nasp-1.1.2.dist-info/entry_points.txt
nasp-1.1.2.dist-info/top_level.txt
