Metadata-Version: 2.1
Name: nasp
Version: 1.1.2
Summary: Northern Arizona SNP Pipeline
Home-page: https://github.com/TGenNorth/nasp
Author: Darrin Lemmer
Author-email: dlemmer@tgen.org
License: Academic and Research License
Keywords: nasp
Platform: UNKNOWN
Classifier: Development Status :: 5 - Production/Stable
Classifier: Environment :: Console
Classifier: Intended Audience :: Developers
Classifier: Intended Audience :: Science/Research
Classifier: Natural Language :: English
Classifier: Operating System :: POSIX
Classifier: Programming Language :: Python :: 3
Classifier: Programming Language :: Python :: 3.3
Classifier: Programming Language :: Python :: 3.4
Classifier: Topic :: Scientific/Engineering :: Bio-Informatics
